.project
.pydevproject
gendocwafo.py
manifest
setup.py
setup_old.py
src/epydoc_wafo.prj
src/Wafo.egg-info/PKG-INFO
src/Wafo.egg-info/SOURCES.txt
src/Wafo.egg-info/dependency_links.txt
src/Wafo.egg-info/top_level.txt
src/wafo/SpecData1D.mm
src/wafo/__init__.py
src/wafo/c_library.pyd
src/wafo/data_structures.py
src/wafo/dctpack.py
src/wafo/definitions.py
src/wafo/definitions.~py
src/wafo/demo_sg.py
src/wafo/gaussian.py
src/wafo/info.py
src/wafo/integrate.py
src/wafo/interpolate.py
src/wafo/kdetools.py
src/wafo/meshgrid.py
src/wafo/misc.py
src/wafo/mvn.pyd
src/wafo/mvn.pyf
src/wafo/mvndst.f
src/wafo/mvnprdmod.pyd
src/wafo/namedtuple.py
src/wafo/objects.py
src/wafo/plotbackend.py
src/wafo/polynomial.py
src/wafo/polynomial_old.py
src/wafo/ppimport.py
src/wafo/rindmod.pyd
src/wafo/sg_filter.py
src/wafo/test_ppimport.py
src/wafo/wafodata.py
src/wafo.egg-info/SOURCES.txt
src/wafo/covariance/__init__.py
src/wafo/covariance/core.py
src/wafo/data/__init__.py
src/wafo/data/atlantic.dat
src/wafo/data/gfaks89.dat
src/wafo/data/gfaksr89.dat
src/wafo/data/info.py
src/wafo/data/info.~py
src/wafo/data/japansea.dat
src/wafo/data/northsea.dat
src/wafo/data/sea.dat
src/wafo/data/sea.m
src/wafo/data/sfa89.dat
src/wafo/data/sn.dat
src/wafo/data/wafoLogoNewWithBorder.png
src/wafo/data/wafoLogoNewWithBorder.svg
src/wafo/data/wafoLogoNewWithoutBorder.png
src/wafo/data/wafoLogoNewWithoutBorder.svg
src/wafo/data/wafologoWithBorder.png
src/wafo/data/yura87.dat
src/wafo/source/c_codes/build_all.py
src/wafo/source/c_codes/c_functions.c
src/wafo/source/c_codes/c_library.pyd
src/wafo/source/c_codes/c_library.pyf
src/wafo/source/c_codes/old/build_all_.py
src/wafo/source/c_codes/old/diffsumfunq.pyd
src/wafo/source/c_codes/old/diffsumfunq.pyf
src/wafo/source/c_codes/old/disufq.pyf
src/wafo/source/c_codes/old/disufq1.c
src/wafo/source/c_codes/old/findcross.c
src/wafo/source/c_codes/old/findrfc.c
src/wafo/source/c_codes/old/rfc.pyd
src/wafo/source/c_codes/old/rfc.pyf
src/wafo/source/cov2XXXpdf/cov2acdf.f
src/wafo/source/cov2XXXpdf/cov2mmpdf.f
src/wafo/source/cov2XXXpdf/cov2mmtpdf.f
src/wafo/source/cov2XXXpdf/cov2tccpdf.f
