Metadata-Version: 1.0
Name: wafo
Version: 0.11
Summary: UNKNOWN
Home-page: http://code.google.com/p/pywafo/
Author: WAFO-group
Author-email: wafo@maths.lth.se
License: GPL
Platform: UNKNOWN
Classifier: Development Status :: 4 - Beta
Classifier: Intended Audience :: Education
Classifier: Intended Audience :: Science/Research
Classifier: License :: OSI Approved :: GNU General Public License (GPL)
Classifier: Operating System :: Microsoft :: Windows
Classifier: Programming Language :: Python :: 2.6
Classifier: Topic :: Scientific/Engineering :: Mathematics
